dictionary_client/__init__.py
dictionary_client/commands.py
dictionary_client/dictionary_client.py
dictionary_client/response.py
dictionary_client/response.py~
dictionary_client/status_codes.py
dictionary_client/utils.py
dictionary_client/word.py
py_dict_client-0.2.0.dist-info/LICENSE
py_dict_client-0.2.0.dist-info/METADATA
py_dict_client-0.2.0.dist-info/WHEEL
py_dict_client-0.2.0.dist-info/top_level.txt
py_dict_client-0.2.0.dist-info/RECORD
