Metadata-Version: 2.1
Name: py-dict-client
Version: 0.2.0
Summary: A client implementing the Dictionary Server Protocol (DICT)
Home-page: https://github.com/jams2/py-dict-client
Author: Joshua Munn
Author-email: public@elysee-munn.family
License: UNKNOWN
Keywords: dictionary language definition server client
Platform: UNKNOWN
Classifier: Development Status :: 3 - Alpha
Classifier: Intended Audience :: Developers
Classifier: License :: OSI Approved :: GNU General Public License v3 (GPLv3)
Classifier: Programming Language :: Python :: 3
Requires-Python: >=3
License-File: LICENSE
Provides-Extra: dev
Requires-Dist: nose2 ; extra == 'dev'
Requires-Dist: coverage ; extra == 'dev'
Requires-Dist: pylint ; extra == 'dev'
Requires-Dist: flake8 ; extra == 'dev'
Requires-Dist: black ; extra == 'dev'
Requires-Dist: isort ; extra == 'dev'
Provides-Extra: dist
Requires-Dist: setuptools ; extra == 'dist'
Requires-Dist: wheel ; extra == 'dist'
Requires-Dist: twine ; extra == 'dist'
